signalboa_python_connector/__init__.py
signalboa_python_connector/__main__.py
signalboa_python_connector/__version__.py
signalboa_python_connector/api_connector.py
signalboa_python_connector/enums.py
signalboa_python_connector/exceptions.py
signalboa-0.19.dist-info/LICENSE
signalboa-0.19.dist-info/METADATA
signalboa-0.19.dist-info/WHEEL
signalboa-0.19.dist-info/top_level.txt
signalboa-0.19.dist-info/RECORD
