Metadata-Version: 2.1
Name: signalboa
Version: 0.19
Summary: Connector for SingalBoa user Api
Home-page: https://github.com/brainalyzed/signalboa
Author: Thomas Kopetsch
Author-email: thomas@brainalyzed.com
License: Brainalyzed
Project-URL: Bug Tracker, https://github.com/brainalyzed/signalboa/issues
Keywords: signalboa
Platform: UNKNOWN
Classifier: Programming Language :: Python :: 3
Classifier: License :: OSI Approved :: MIT License
Classifier: Operating System :: OS Independent
Requires-Python: >=3.7
License-File: LICENSE
Requires-Dist: requests
Provides-Extra: test
Requires-Dist: pytest (>=6.2.5) ; extra == 'test'
Requires-Dist: flake8 (>=4.0.1) ; extra == 'test'
Requires-Dist: pytest-custom-exit-code (>=0.3.0) ; extra == 'test'
